{"v":"5.5.2","fr":10,"ip":0,"op":27,"w":400,"h":400,"nm":"Comp 1","ddd":0,"assets":[],"fonts":{"list":[{"fName":"NotoSans-Bold","fFamily":"Noto Sans","fStyle":"Bold","ascent":75.9994506835938}]},"layers":[{"ddd":0,"ind":1,"ty":4,"nm":"Shape Layer 2","td":1,"sr":1,"ks":{"o":{"a":0,"k":100,"ix":11},"r":{"a":0,"k":0,"ix":10},"p":{"a":0,"k":[658,984,0],"ix":2},"a":{"a":0,"k":[0,0,0],"ix":1},"s":{"a":0,"k":[130,130,100],"ix":6}},"ao":0,"shapes":[{"ty":"gr","it":[{"d":1,"ty":"el","s":{"a":0,"k":[240,240],"ix":2},"p":{"a":0,"k":[0,0],"ix":3},"nm":"Ellipse Path 1","mn":"ADBE Vector Shape - Ellipse","hd":false},{"ty":"st","c":{"a":0,"k":[0,0.4588235294117647,1,1],"ix":3},"o":{"a":0,"k":100,"ix":4},"w":{"a":0,"k":2,"ix":5},"lc":1,"lj":1,"ml":4,"bm":0,"nm":"Stroke 1","mn":"ADBE Vector Graphic - Stroke","hd":false},{"ty":"fl","c":{"a":0,"k":[0,0.4470588235294118,0.9764705882352941,1],"ix":4},"o":{"a":0,"k":100,"ix":5},"r":1,"bm":0,"nm":"Fill 1","mn":"ADBE Vector Graphic - Fill","hd":false},{"ty":"tr","p":{"a":0,"k":[-352.65,-603.797],"ix":2},"a":{"a":0,"k":[0,0],"ix":1},"s":{"a":0,"k":[120,120],"ix":3},"r":{"a":0,"k":0,"ix":6},"o":{"a":0,"k":50,"ix":7},"sk":{"a":0,"k":0,"ix":4},"sa":{"a":0,"k":0,"ix":5},"nm":"Transform"}],"nm":"Ellipse 1","np":3,"cix":2,"bm":0,"ix":1,"mn":"ADBE Vector Group","hd":false}],"ip":0,"op":900.000036657751,"st":0,"bm":0},{"ddd":0,"ind":2,"ty":5,"nm":"73 44 22 31 43 04 09 56 74 88 93 34 88 92 28 43 03 08 87 63 21 64 88 ","tt":1,"sr":1,"ks":{"o":{"a":0,"k":100,"ix":11},"r":{"a":0,"k":0,"ix":10},"p":{"a":1,"k":[{"i":{"x":0.833,"y":0.833},"o":{"x":0.167,"y":0.167},"t":0,"s":[266,336,0],"to":[-3,-856,0],"ti":[3,856,0]},{"t":26.0000010590017,"s":[248,-4800,0]}],"ix":2},"a":{"a":0,"k":[0,0,0],"ix":1},"s":{"a":0,"k":[150,150,100],"ix":6}},"ao":0,"t":{"d":{"k":[{"s":{"sz":[216.727233886719,5028],"ps":[-152,-148],"s":130,"f":"NotoSans-Bold","t":"73\r44\r22\r31\r43\r04\r09\r56\r74\r88\r93\r34\r88\r92\r28\r43\r03\r08\r87\r63\r21\r64\r88\r","j":2,"tr":0,"lh":200,"ls":0,"fc":[1,0.804,0]},"t":0}]},"p":{},"m":{"g":1,"a":{"a":0,"k":[0,0],"ix":2}},"a":[]},"ip":0,"op":900.000036657751,"st":0,"bm":0}],"markers":[],"chars":[{"ch":"7","size":130,"style":"Bold","w":55.08,"data":{"shapes":[{"ty":"gr","it":[{"ind":0,"ty":"sh","ix":1,"ks":{"a":0,"k":{"i":[[0,0],[0,0],[0,0],[0,0],[0,0],[0,0],[0,0]],"o":[[0,0],[0,0],[0,0],[0,0],[0,0],[0,0],[0,0]],"v":[[25.879,0],[51.904,-61.816],[51.904,-71.289],[2.686,-71.289],[2.686,-58.594],[35.498,-58.594],[10.107,0]],"c":true},"ix":2},"nm":"7","mn":"ADBE Vector Shape - Group","hd":false}],"nm":"7","np":3,"cix":2,"bm":0,"ix":1,"mn":"ADBE Vector Group","hd":false}]},"fFamily":"Noto Sans"},{"ch":"3","size":130,"style":"Bold","w":55.08,"data":{"shapes":[{"ty":"gr","it":[{"ind":0,"ty":"sh","ix":1,"ks":{"a":0,"k":{"i":[[1.123,2.1],[2.051,1.449],[2.881,0.765],[3.516,0],[2.18,-0.358],[1.888,-0.635],[1.611,-0.846],[1.367,-1.009],[0,0],[-0.961,0.57],[-1.156,0.472],[-1.351,0.31],[-1.562,0],[-1.579,-1.432],[0,-2.539],[0.488,-1.237],[1.188,-0.928],[1.985,-0.537],[2.995,0],[0,0],[0,0],[0,0],[-2.181,-0.455],[-1.351,-0.83],[-0.603,-1.188],[0,-1.465],[0.471,-1.318],[1.106,-0.944],[1.855,-0.52],[2.799,0],[1.579,0.195],[1.627,0.407],[1.627,0.586],[1.465,0.781],[0,0],[-3.386,-0.635],[-3.841,0],[-3.532,1.09],[-2.328,1.953],[-1.123,2.654],[0,3.125],[2.962,2.783],[5.762,0.716],[0,0],[-1.872,0.993],[-1.384,1.482],[-0.798,1.97],[0,2.474]],"o":[[-1.123,-2.1],[-2.051,-1.448],[-2.881,-0.764],[-2.474,0],[-2.181,0.359],[-1.888,0.635],[-1.611,0.847],[0,0],[0.781,-0.553],[0.96,-0.569],[1.155,-0.471],[1.35,-0.309],[3.418,0],[1.579,1.433],[0,1.4],[-0.488,1.237],[-1.189,0.928],[-1.986,0.537],[0,0],[0,0],[0,0],[3.19,0],[2.18,0.456],[1.35,0.83],[0.602,1.189],[0,1.562],[-0.472,1.318],[-1.107,0.945],[-1.855,0.521],[-1.4,0],[-1.579,-0.195],[-1.628,-0.407],[-1.628,-0.586],[0,0],[2.93,1.302],[3.385,0.635],[4.785,0],[3.532,-1.09],[2.327,-1.953],[1.123,-2.653],[0,-4.72],[-2.962,-2.783],[0,0],[2.18,-0.52],[1.871,-0.993],[1.383,-1.481],[0.797,-1.969],[0,-2.702]],"v":[[47.437,-62.622],[42.676,-67.944],[35.278,-71.265],[25.684,-72.412],[18.701,-71.875],[12.598,-70.386],[7.349,-68.164],[2.881,-65.381],[10.498,-55.322],[13.11,-57.007],[16.284,-58.569],[20.044,-59.741],[24.414,-60.205],[31.909,-58.057],[34.277,-52.1],[33.545,-48.145],[31.03,-44.897],[26.27,-42.7],[18.799,-41.895],[13.818,-41.895],[13.818,-31.299],[18.896,-31.299],[26.953,-30.615],[32.251,-28.687],[35.181,-25.659],[36.084,-21.68],[35.376,-17.358],[33.008,-13.965],[28.564,-11.768],[21.582,-10.986],[17.114,-11.279],[12.305,-12.183],[7.422,-13.672],[2.783,-15.723],[2.783,-2.881],[12.256,0.024],[23.096,0.977],[35.571,-0.659],[44.36,-5.225],[49.536,-12.134],[51.221,-20.801],[46.777,-32.056],[33.691,-37.305],[33.691,-37.598],[39.771,-39.868],[44.653,-43.579],[47.925,-48.755],[49.121,-55.42]],"c":true},"ix":2},"nm":"3","mn":"ADBE Vector Shape - Group","hd":false}],"nm":"3","np":3,"cix":2,"bm":0,"ix":1,"mn":"ADBE Vector Group","hd":false}]},"fFamily":"Noto Sans"},{"ch":"\r","size":130,"style":"Bold","w":0,"fFamily":"Noto Sans"},{"ch":"4","size":130,"style":"Bold","w":55.08,"data":{"shapes":[{"ty":"gr","it":[{"ind":0,"ty":"sh","ix":1,"ks":{"a":0,"k":{"i":[[0,0],[0,0],[0,0],[0,0],[0,0],[0,0],[0,0],[0,0],[0,0],[0,0],[0,0]],"o":[[0,0],[0,0],[0,0],[0,0],[0,0],[0,0],[0,0],[0,0],[0,0],[0,0],[0,0]],"v":[[52.979,-26.514],[44.385,-26.514],[44.385,-71.387],[30.518,-71.387],[0.195,-25.293],[0.195,-14.795],[29.688,-14.795],[29.688,0],[44.385,0],[44.385,-14.795],[52.979,-14.795]],"c":true},"ix":2},"nm":"4","mn":"ADBE Vector Shape - Group","hd":false},{"ind":1,"ty":"sh","ix":2,"ks":{"a":0,"k":{"i":[[0,0],[0,0],[-0.732,1.53],[-0.586,1.367],[0,0],[0.049,-0.732],[0.049,-0.977],[0.049,-1.074],[0.032,-1.009],[0.016,-0.797],[0,-0.423],[0,0]],"o":[[0,0],[0.944,-1.53],[0.732,-1.53],[0,0],[-0.033,0.326],[-0.049,0.732],[-0.049,0.977],[-0.049,1.074],[-0.033,1.009],[-0.017,0.798],[0,0],[0,0]],"v":[[13.477,-26.514],[25.391,-44.58],[27.905,-49.17],[29.883,-53.516],[30.322,-53.516],[30.2,-51.929],[30.054,-49.365],[29.907,-46.289],[29.785,-43.164],[29.712,-40.454],[29.688,-38.623],[29.688,-26.514]],"c":true},"ix":2},"nm":"4","mn":"ADBE Vector Shape - Group","hd":false}],"nm":"4","np":5,"cix":2,"bm":0,"ix":1,"mn":"ADBE Vector Group","hd":false}]},"fFamily":"Noto Sans"},{"ch":"2","size":130,"style":"Bold","w":55.08,"data":{"shapes":[{"ty":"gr","it":[{"ind":0,"ty":"sh","ix":1,"ks":{"a":0,"k":{"i":[[0,0],[0,0],[0,0],[0,0],[-2.23,2.425],[-1.693,2.458],[-0.977,2.556],[0,2.8],[1.025,2.474],[1.92,1.742],[2.718,0.945],[3.418,0],[2.311,-0.569],[1.92,-0.944],[1.595,-1.221],[1.465,-1.334],[0,0],[-2.377,1.27],[-2.572,0],[-1.449,-1.334],[0,-2.409],[0.684,-1.888],[1.237,-1.823],[1.725,-1.92],[2.116,-2.278],[0,0],[0,0],[0,0]],"o":[[0,0],[0,0],[0,0],[2.539,-2.506],[2.229,-2.425],[1.692,-2.457],[0.977,-2.555],[0,-3.092],[-1.025,-2.473],[-1.921,-1.741],[-2.718,-0.944],[-2.865,0],[-2.312,0.57],[-1.921,0.945],[-1.595,1.221],[0,0],[2.604,-2.344],[2.376,-1.27],[2.441,0],[1.448,1.335],[0,2.181],[-0.684,1.888],[-1.237,1.823],[-1.726,1.921],[0,0],[0,0],[0,0],[0,0]],"v":[[51.904,-12.695],[22.803,-12.695],[22.803,-13.379],[31.396,-22.021],[38.55,-29.419],[44.434,-36.743],[48.438,-44.263],[49.902,-52.295],[48.364,-60.645],[43.945,-66.968],[36.987,-70.996],[27.783,-72.412],[20.02,-71.558],[13.672,-69.287],[8.398,-66.04],[3.809,-62.207],[12.012,-52.49],[19.482,-57.91],[26.904,-59.814],[32.739,-57.812],[34.912,-52.197],[33.887,-46.094],[31.006,-40.527],[26.562,-34.912],[20.801,-28.613],[4.004,-10.498],[4.004,0],[51.904,0]],"c":true},"ix":2},"nm":"2","mn":"ADBE Vector Shape - Group","hd":false}],"nm":"2","np":3,"cix":2,"bm":0,"ix":1,"mn":"ADBE Vector Group","hd":false}]},"fFamily":"Noto Sans"},{"ch":"1","size":130,"style":"Bold","w":55.08,"data":{"shapes":[{"ty":"gr","it":[{"ind":0,"ty":"sh","ix":1,"ks":{"a":0,"k":{"i":[[0,0],[0,0],[0,0],[0,0],[0,0],[-0.521,0.488],[-0.488,0.472],[-0.391,0.391],[-0.163,0.195],[0.049,-1.302],[0.049,-1.286],[0.016,-1.188],[0,-0.846],[0,0],[0,0]],"o":[[0,0],[0,0],[0,0],[0,0],[0.488,-0.391],[0.52,-0.488],[0.488,-0.471],[0.391,-0.391],[-0.033,1.074],[-0.049,1.302],[-0.049,1.286],[-0.017,1.189],[0,0],[0,0],[0,0]],"v":[[39.893,-71.387],[27.49,-71.387],[4.492,-53.076],[11.816,-43.994],[20.02,-50.586],[21.533,-51.904],[23.047,-53.345],[24.365,-54.639],[25.195,-55.518],[25.073,-51.953],[24.927,-48.071],[24.829,-44.36],[24.805,-41.309],[24.805,0],[39.893,0]],"c":true},"ix":2},"nm":"1","mn":"ADBE Vector Shape - Group","hd":false}],"nm":"1","np":3,"cix":2,"bm":0,"ix":1,"mn":"ADBE Vector Group","hd":false}]},"fFamily":"Noto Sans"},{"ch":"0","size":130,"style":"Bold","w":55.08,"data":{"shapes":[{"ty":"gr","it":[{"ind":0,"ty":"sh","ix":1,"ks":{"a":0,"k":{"i":[[1.009,4.558],[2.051,3.158],[3.059,1.66],[4.102,0],[3.092,-1.676],[1.953,-3.157],[0.895,-4.557],[0,-5.762],[-0.993,-4.524],[-2.019,-3.157],[-3.06,-1.66],[-4.134,0],[-3.109,1.66],[-1.97,3.158],[-0.896,4.525],[0,5.762]],"o":[[-1.009,-4.557],[-2.051,-3.157],[-3.06,-1.66],[-4.395,0],[-3.093,1.677],[-1.953,3.158],[-0.896,4.558],[0,5.762],[0.993,4.525],[2.018,3.158],[3.059,1.66],[4.395,0],[3.108,-1.66],[1.969,-3.157],[0.895,-4.524],[0,-5.794]],"v":[[50.488,-51.221],[45.898,-62.793],[38.232,-70.02],[27.49,-72.51],[16.26,-69.995],[8.691,-62.744],[4.419,-51.172],[3.076,-35.693],[4.565,-20.264],[9.082,-8.74],[16.699,-1.514],[27.49,0.977],[38.745,-1.514],[46.362,-8.74],[50.659,-20.264],[52.002,-35.693]],"c":true},"ix":2},"nm":"0","mn":"ADBE Vector Shape - Group","hd":false},{"ind":1,"ty":"sh","ix":2,"ks":{"a":0,"k":{"i":[[-0.326,3.076],[-0.749,2.051],[-1.189,1.042],[-1.726,0],[-1.482,-4.118],[0,-8.17],[1.481,-4.069],[3.385,0],[1.399,4.102],[0,8.138]],"o":[[0.325,-3.076],[0.748,-2.051],[1.188,-1.041],[3.385,0],[1.481,4.118],[0,8.203],[-1.482,4.07],[-3.451,0],[-1.4,-4.102],[0,-4.069]],"v":[[18.604,-46.411],[20.215,-54.102],[23.12,-58.74],[27.49,-60.303],[34.79,-54.126],[37.012,-35.693],[34.79,-17.285],[27.49,-11.182],[20.215,-17.334],[18.115,-35.693]],"c":true},"ix":2},"nm":"0","mn":"ADBE Vector Shape - Group","hd":false}],"nm":"0","np":5,"cix":2,"bm":0,"ix":1,"mn":"ADBE Vector Group","hd":false}]},"fFamily":"Noto Sans"},{"ch":"9","size":130,"style":"Bold","w":55.08,"data":{"shapes":[{"ty":"gr","it":[{"ind":0,"ty":"sh","ix":1,"ks":{"a":0,"k":{"i":[[1.302,3.939],[2.246,2.572],[3.059,1.254],[3.516,0],[2.881,-1.139],[2.018,-2.132],[1.09,-3.059],[0,-3.873],[-0.912,-2.799],[-1.709,-1.92],[-2.474,-1.009],[-3.093,0],[-1.562,0.423],[-1.237,0.749],[-0.912,1.009],[-0.652,1.172],[0,0],[0.7,-2.734],[1.66,-1.969],[2.832,-1.09],[4.395,0],[1.383,0.179],[1.204,0.326],[0,0],[-0.781,-0.082],[-0.83,-0.049],[-0.814,-0.033],[-0.684,0],[-3.532,1.123],[-2.523,1.953],[-1.644,2.686],[-0.961,3.093],[-0.375,3.402],[0,3.418]],"o":[[-1.302,-3.938],[-2.246,-2.571],[-3.06,-1.253],[-3.581,0],[-2.881,1.14],[-2.019,2.132],[-1.091,3.06],[0,3.613],[0.911,2.8],[1.709,1.921],[2.473,1.009],[1.92,0],[1.562,-0.423],[1.237,-0.748],[0.911,-1.009],[0,0],[-0.163,3.288],[-0.7,2.734],[-1.66,1.97],[-2.832,1.091],[-1.433,0],[-1.384,-0.179],[0,0],[0.586,0.13],[0.781,0.081],[0.83,0.049],[0.813,0.032],[4.752,0],[3.532,-1.123],[2.522,-1.953],[1.643,-2.686],[0.96,-3.092],[0.374,-3.401],[0,-5.338]],"v":[[49.561,-54.834],[44.238,-64.6],[36.279,-70.337],[26.416,-72.217],[16.724,-70.508],[9.375,-65.601],[4.712,-57.812],[3.076,-47.412],[4.443,-37.793],[8.374,-30.713],[14.648,-26.318],[22.998,-24.805],[28.223,-25.439],[32.422,-27.197],[35.645,-29.834],[37.988,-33.105],[38.623,-33.105],[37.329,-24.072],[33.789,-17.017],[27.051,-12.427],[16.211,-10.791],[11.987,-11.06],[8.105,-11.816],[8.105,0.293],[10.156,0.61],[12.573,0.806],[15.039,0.928],[17.285,0.977],[29.712,-0.708],[38.794,-5.322],[45.044,-12.28],[48.95,-20.947],[50.952,-30.688],[51.514,-40.918]],"c":true},"ix":2},"nm":"9","mn":"ADBE Vector Shape - Group","hd":false},{"ind":1,"ty":"sh","ix":2,"ks":{"a":0,"k":{"i":[[-1.221,-0.813],[-0.83,-1.318],[-0.407,-1.643],[0,-1.66],[0.471,-1.172],[0.879,-0.944],[1.237,-0.586],[1.497,0],[1.465,2.019],[0,3.451],[-0.439,1.579],[-0.798,1.025],[-1.107,0.488],[-1.335,0]],"o":[[1.221,0.814],[0.83,1.318],[0.407,1.644],[0,1.205],[-0.472,1.172],[-0.879,0.945],[-1.237,0.586],[-2.962,0],[-1.465,-2.018],[0,-2.148],[0.439,-1.579],[0.797,-1.025],[1.106,-0.488],[1.627,0]],"v":[[30.981,-58.887],[34.058,-55.688],[35.913,-51.245],[36.523,-46.289],[35.815,-42.725],[33.789,-39.551],[30.615,-37.256],[26.514,-36.377],[19.873,-39.404],[17.676,-47.607],[18.335,-53.198],[20.19,-57.104],[23.047,-59.375],[26.709,-60.107]],"c":true},"ix":2},"nm":"9","mn":"ADBE Vector Shape - Group","hd":false}],"nm":"9","np":5,"cix":2,"bm":0,"ix":1,"mn":"ADBE Vector Group","hd":false}]},"fFamily":"Noto Sans"},{"ch":"5","size":130,"style":"Bold","w":55.08,"data":{"shapes":[{"ty":"gr","it":[{"ind":0,"ty":"sh","ix":1,"ks":{"a":0,"k":{"i":[[1.383,-0.227],[1.041,-0.227],[0,0],[0,0],[0,0],[0,0],[0,0],[0,0],[-0.847,0.179],[-0.928,0.163],[-0.961,0.098],[-0.847,0],[-2.23,-1.839],[0,-3.516],[2.278,-1.807],[4.362,0],[1.627,0.244],[1.611,0.407],[1.497,0.57],[1.139,0.652],[0,0],[-1.449,-0.488],[-1.611,-0.309],[-1.758,-0.163],[-1.791,0],[-3.467,1.139],[-2.344,2.132],[-1.205,3.076],[0,3.874],[1.106,2.718],[1.953,1.823],[2.637,0.945],[3.059,0]],"o":[[-1.384,0.228],[0,0],[0,0],[0,0],[0,0],[0,0],[0,0],[0.618,-0.195],[0.846,-0.179],[0.928,-0.163],[0.96,-0.098],[4.655,0],[2.229,1.839],[0,3.939],[-2.279,1.807],[-1.465,0],[-1.628,-0.244],[-1.611,-0.407],[-1.498,-0.569],[0,0],[1.172,0.652],[1.448,0.488],[1.611,0.309],[1.758,0.163],[4.492,0],[3.467,-1.139],[2.344,-2.132],[1.204,-3.076],[0,-3.516],[-1.107,-2.718],[-1.953,-1.823],[-2.637,-0.944],[-2.181,0]],"v":[[23.853,-45.264],[20.215,-44.58],[21.387,-58.594],[45.996,-58.594],[45.996,-71.387],[8.301,-71.387],[5.615,-35.01],[11.621,-31.787],[13.818,-32.349],[16.479,-32.861],[19.312,-33.252],[22.021,-33.398],[32.349,-30.64],[35.693,-22.607],[32.275,-13.989],[22.314,-11.279],[17.676,-11.646],[12.817,-12.622],[8.154,-14.087],[4.199,-15.918],[4.199,-2.881],[8.13,-1.172],[12.72,0.024],[17.773,0.732],[23.096,0.977],[35.034,-0.732],[43.75,-5.64],[49.072,-13.452],[50.879,-23.877],[49.219,-33.228],[44.629,-40.039],[37.744,-44.189],[29.199,-45.605]],"c":true},"ix":2},"nm":"5","mn":"ADBE Vector Shape - Group","hd":false}],"nm":"5","np":3,"cix":2,"bm":0,"ix":1,"mn":"ADBE Vector Group","hd":false}]},"fFamily":"Noto Sans"},{"ch":"6","size":130,"style":"Bold","w":55.08,"data":{"shapes":[{"ty":"gr","it":[{"ind":0,"ty":"sh","ix":1,"ks":{"a":0,"k":{"i":[[-1.286,-3.922],[-2.263,-2.571],[-3.06,-1.253],[-3.516,0],[-2.865,1.123],[-2.019,2.132],[-1.091,3.06],[0,3.874],[0.911,2.8],[1.709,1.921],[2.473,1.009],[3.092,0],[1.546,-0.423],[1.237,-0.732],[0.928,-1.025],[0.651,-1.172],[0,0],[-0.7,2.734],[-1.66,1.953],[-2.832,1.091],[-4.395,0],[-1.384,-0.179],[-1.237,-0.293],[0,0],[0.781,0.098],[0.83,0.049],[0.813,0.033],[0.684,0],[3.532,-1.123],[2.522,-1.969],[1.643,-2.669],[0.96,-3.108],[0.374,-3.385],[0,-3.418]],"o":[[1.286,3.923],[2.262,2.572],[3.059,1.253],[3.58,0],[2.864,-1.123],[2.018,-2.132],[1.09,-3.059],[0,-3.613],[-0.912,-2.799],[-1.709,-1.92],[-2.474,-1.009],[-1.921,0],[-1.546,0.423],[-1.237,0.732],[-0.928,1.025],[0,0],[0.163,-3.32],[0.7,-2.734],[1.66,-1.953],[2.832,-1.09],[1.399,0],[1.383,0.179],[0,0],[-0.619,-0.13],[-0.781,-0.098],[-0.83,-0.049],[-0.814,-0.032],[-4.72,0],[-3.532,1.123],[-2.523,1.97],[-1.644,2.67],[-0.961,3.109],[-0.375,3.386],[0,5.371]],"v":[[5.64,-16.382],[10.962,-6.641],[18.945,-0.903],[28.809,0.977],[38.477,-0.708],[45.801,-5.591],[50.464,-13.379],[52.1,-23.779],[50.732,-33.398],[46.802,-40.479],[40.527,-44.873],[32.178,-46.387],[26.978,-45.752],[22.803,-44.019],[19.556,-41.382],[17.188,-38.086],[16.602,-38.086],[17.896,-47.168],[21.436,-54.199],[28.174,-58.765],[39.014,-60.4],[43.188,-60.132],[47.119,-59.424],[47.119,-71.484],[45.02,-71.826],[42.603,-72.046],[40.137,-72.168],[37.891,-72.217],[25.513,-70.532],[16.431,-65.894],[10.181,-58.936],[6.274,-50.269],[4.272,-40.527],[3.711,-30.322]],"c":true},"ix":2},"nm":"6","mn":"ADBE Vector Shape - Group","hd":false},{"ind":1,"ty":"sh","ix":2,"ks":{"a":0,"k":{"i":[[1.221,0.814],[0.83,1.318],[0.407,1.644],[0,1.66],[-0.472,1.172],[-0.879,0.945],[-1.237,0.586],[-1.498,0],[-1.449,-2.002],[0,-3.483],[0.439,-1.562],[0.797,-1.025],[1.09,-0.504],[1.334,0]],"o":[[-1.221,-0.813],[-0.83,-1.318],[-0.407,-1.643],[0,-1.204],[0.471,-1.172],[0.879,-0.944],[1.237,-0.586],[2.962,0],[1.448,2.002],[0,2.148],[-0.439,1.562],[-0.798,1.025],[-1.091,0.505],[-1.628,0]],"v":[[24.243,-12.305],[21.167,-15.503],[19.312,-19.946],[18.701,-24.902],[19.409,-28.467],[21.436,-31.641],[24.609,-33.936],[28.711,-34.814],[35.327,-31.812],[37.5,-23.584],[36.841,-18.018],[34.985,-14.136],[32.153,-11.841],[28.516,-11.084]],"c":true},"ix":2},"nm":"6","mn":"ADBE Vector Shape - Group","hd":false}],"nm":"6","np":5,"cix":2,"bm":0,"ix":1,"mn":"ADBE Vector Group","hd":false}]},"fFamily":"Noto Sans"},{"ch":"8","size":130,"style":"Bold","w":55.08,"data":{"shapes":[{"ty":"gr","it":[{"ind":0,"ty":"sh","ix":1,"ks":{"a":0,"k":{"i":[[2.637,-0.716],[2.018,-1.448],[1.188,-2.132],[0,-2.832],[-0.603,-1.758],[-1.025,-1.448],[-1.4,-1.188],[-1.595,-1.009],[1.66,-1.204],[1.237,-1.562],[0.716,-1.953],[0,-2.441],[-1.058,-2.376],[-2.051,-1.627],[-2.995,-0.879],[-3.841,0],[-2.946,0.911],[-2.116,1.693],[-1.172,2.409],[0,2.962],[0.846,1.921],[1.399,1.546],[1.807,1.237],[1.888,1.009],[-1.562,1.107],[-1.14,1.416],[-0.652,1.742],[0,2.148],[1.172,2.148],[1.985,1.433],[2.637,0.716],[2.962,0]],"o":[[-2.637,0.716],[-2.019,1.449],[-1.189,2.132],[0,2.116],[0.602,1.758],[1.025,1.449],[1.399,1.189],[-1.888,0.912],[-1.66,1.205],[-1.237,1.562],[-0.716,1.953],[0,2.962],[1.057,2.377],[2.051,1.628],[2.995,0.879],[3.548,0],[2.946,-0.911],[2.116,-1.692],[1.172,-2.409],[0,-2.376],[-0.847,-1.92],[-1.4,-1.546],[-1.807,-1.237],[1.823,-0.911],[1.562,-1.106],[1.139,-1.416],[0.651,-1.741],[0,-2.897],[-1.172,-2.148],[-1.986,-1.432],[-2.637,-0.716],[-2.898,0]],"v":[[19.287,-71.24],[12.305,-67.993],[7.495,-62.622],[5.713,-55.176],[6.616,-49.365],[9.058,-44.556],[12.695,-40.601],[17.188,-37.305],[11.865,-34.131],[7.52,-29.98],[4.59,-24.707],[3.516,-18.115],[5.103,-10.107],[9.766,-4.102],[17.334,-0.342],[27.588,0.977],[37.329,-0.391],[44.922,-4.297],[49.854,-10.449],[51.611,-18.506],[50.342,-24.951],[46.973,-30.151],[42.163,-34.326],[36.621,-37.695],[41.699,-40.723],[45.752,-44.507],[48.438,-49.243],[49.414,-55.078],[47.656,-62.646],[42.92,-68.018],[35.986,-71.24],[27.588,-72.314]],"c":true},"ix":2},"nm":"8","mn":"ADBE Vector Shape - Group","hd":false},{"ind":1,"ty":"sh","ix":2,"ks":{"a":0,"k":{"i":[[-0.456,1.172],[-0.83,0.993],[-1.172,0.83],[-1.433,0.716],[0,0],[-1.14,-0.781],[-0.896,-0.928],[-0.57,-1.09],[0,-1.367],[1.692,-1.611],[3.418,0],[1.237,0.439],[0.83,0.781],[0.423,1.091],[0,1.302]],"o":[[0.455,-1.172],[0.83,-0.993],[1.172,-0.83],[0,0],[1.139,0.716],[1.139,0.781],[0.895,0.928],[0.569,1.091],[0,2.637],[-1.693,1.611],[-1.628,0],[-1.237,-0.439],[-0.83,-0.781],[-0.423,-1.09],[0,-1.367]],"v":[[18.164,-22.803],[20.093,-26.05],[23.096,-28.784],[27.002,-31.104],[28.076,-30.42],[31.494,-28.174],[34.546,-25.61],[36.743,-22.583],[37.598,-18.896],[35.059,-12.524],[27.393,-10.107],[23.096,-10.767],[19.995,-12.598],[18.115,-15.405],[17.48,-18.994]],"c":true},"ix":2},"nm":"8","mn":"ADBE Vector Shape - Group","hd":false},{"ind":2,"ty":"sh","ix":3,"ks":{"a":0,"k":{"i":[[-0.945,-0.325],[-0.684,-0.618],[-0.391,-0.911],[0,-1.139],[0.423,-1.009],[0.7,-0.797],[0.911,-0.618],[1.009,-0.52],[0.928,0.603],[0.7,0.765],[0.407,0.993],[0,1.367],[-0.391,0.912],[-0.668,0.619],[-0.928,0.326],[-1.074,0]],"o":[[0.944,0.326],[0.684,0.619],[0.391,0.912],[0,1.302],[-0.423,1.009],[-0.7,0.798],[-0.912,0.619],[-1.042,-0.586],[-0.928,-0.602],[-0.7,-0.764],[-0.407,-0.993],[0,-1.139],[0.391,-0.911],[0.667,-0.618],[0.928,-0.325],[1.106,0]],"v":[[30.566,-60.791],[33.008,-59.375],[34.619,-57.08],[35.205,-54.004],[34.57,-50.537],[32.886,-47.827],[30.469,-45.703],[27.588,-43.994],[24.634,-45.776],[22.192,-47.827],[20.532,-50.464],[19.922,-54.004],[20.508,-57.08],[22.095,-59.375],[24.487,-60.791],[27.49,-61.279]],"c":true},"ix":2},"nm":"8","mn":"ADBE Vector Shape - Group","hd":false}],"nm":"8","np":6,"cix":2,"bm":0,"ix":1,"mn":"ADBE Vector Group","hd":false}]},"fFamily":"Noto Sans"}]}